D_RCNet/API_server.py
D_RCNet/DRCNet.py
D_RCNet/GUI_app.py
D_RCNet/__init__.py
D_RCNet/create_sample.py
D_RCNet/inference.py
D_RCNet/trained_model300.pkl
d_rcnet-0.2.8.dist-info/METADATA
d_rcnet-0.2.8.dist-info/WHEEL
d_rcnet-0.2.8.dist-info/entry_points.txt
d_rcnet-0.2.8.dist-info/top_level.txt
d_rcnet-0.2.8.dist-info/RECORD
